bwq_mcp_demo/__init__.py
bwq_mcp_demo-0.1.0.dist-info/WHEEL
bwq_mcp_demo-0.1.0.dist-info/entry_points.txt
bwq_mcp_demo-0.1.0.dist-info/METADATA
bwq_mcp_demo-0.1.0.dist-info/RECORD
