Metadata-Version: 2.3
Name: bwq-mcp-demo
Version: 0.1.0
Summary: Add your description here
Author: BaiWQ1e
Author-email: BaiWQ1e <fanhuayiluo1@gmail.com>
Requires-Dist: mcp[cli]>=1.18.0
Requires-Python: >=3.13
